Workbook

Sheet COVER
B2: Deal Intelligence Workbook
B4: Workbook Navigation
B5: Tab | C5: Purpose | D5: Key Inputs
B6: INPUTS | C6: Deal assumptions, entry/exit, thesis, NTB names | D6: Company, thesis, entry/exit multiples
B7: FINANCIALS | C7: Raw P&L paste-in area — historical data | D7: Paste actuals here; model pulls from this tab
B8: FINANCIAL MODEL | C8: Operating model — historical + 5yr projections | D8: Projection assumptions (growth, margins)
B9: DRIVER TREE | C9: Thesis decomposition → MOIC by value driver | D9: Upside estimates per driver; NTB linkage
B10: NTB REGISTRY | C10: NTB diligence tracker — evidence & MOIC | D10: Evidence status, MOIC impact, gaps
B11: KPI TREE | C11: KPI hierarchy mapped to financial model | D11: Budget vs. actual; management plan audit
B12: MOIC BRIDGE | C12: MOIC waterfall — entry to exit by NTB contribution | D12: Pulls from NTB Registry and INPUTS
B14: Color Coding
B15: Color | C15: Meaning | D15: Action required
B16: BLUE text on YELLOW | C16: BLUE text on YELLOW | D16: Hardcoded input — change for your deal
B17: BLACK text | C17: BLACK text | D17: Formula — do not overwrite
B18: GREEN text | C18: GREEN text | D18: Links from another tab — do not overwrite
B19: Green background | C19: Green background | D19: Confirmed / PASS status
B20: Orange background | C20: Orange background | D20: Partial / needs attention
B21: Red background | C21: Red background | D21: Gap / CRITICAL — needs resolution

Sheet INPUTS
B2: Deal Inputs
B4: Company & Deal
B5: Field | C5: Value
B6: Company Name
B7: Deal Type
B8: Sector
B9: Investment Thesis (one sentence)
B10: Entry Year
B11: Exit Year (projected)
B13: Entry Assumptions
B14: Metric ($M unless noted) | C14: Value
B15: Entry Revenue ($M)
B16: Entry EBITDA ($M)
B17: Entry EBITDA Margin
B18: Entry EV/EBITDA Multiple
B19: Entry EV ($M) | C19: =INPUTS!B13*INPUTS!B16
B20: Net Debt at Entry ($M)
B21: Equity Invested ($M) | C21: =INPUTS!B20-INPUTS!B21
B23: Exit Assumptions
B24: Metric | C24: Value
B25: Exit Revenue ($M)
B26: Exit EBITDA ($M)
B27: Exit EV/EBITDA Multiple
B28: Exit EV ($M)
B29: Net Debt at Exit ($M)
B30: Proceeds to Equity ($M)
B32: Returns Summary
B33: Metric | C33: Value
B34: Gross MOIC | C34: =IFERROR(INPUTS!B36/INPUTS!B22,"-")
B35: Holding Period (Years) | C35: =IFERROR(INPUTS!B6-INPUTS!B5,"-")
B37: NTB Registry — Names
B38: Define your 5-7 Need-to-Believes here. Referenced across all tabs.
B39: NTB # | C39: NTB Statement
B40: NTB 1
B41: NTB 2
B42: NTB 3
B43: NTB 4
B44: NTB 5
B45: NTB 6
B46: NTB 7

Sheet FINANCIALS
B2: Historical Financials — Paste Input Area
B4: Paste your actuals here. Financial Model tab pulls from this sheet. Units: $M unless noted.
B6: Line Item | C6: FY-3 | D6: FY-2 | E6: FY-1 | F6: FY0 | G6: Notes / Source
B7: INCOME STATEMENT
B8: Revenue ($M)
B9: YoY Growth %
B10: Cost of Revenue ($M)
B11: Gross Profit ($M)
B12: Gross Margin %
B13: Sales & Marketing ($M)
B14: Research & Development ($M)
B15: General & Administrative ($M)
B16: Total Operating Expenses ($M)
B17: EBITDA ($M)
B18: EBITDA Margin %
... B35: Free Cash Flow ($M)

Sheet FINANCIAL MODEL
B2: Financial Model — Historical & Projections
B4: Line Item ($M) | C4: FY-3 | D4: FY-2 | E4: FY-1 | F4: FY0 | G4: FY1 | H4: FY2 | I4: FY3 | J4: FY4 | K4: FY5 | L4: Notes
B5: Projection Assumptions
B6: Yellow cells = inputs. Change these for your projections.
B7: Revenue Growth %
B8: Gross Margin %
B9: S&M % of Revenue
B10: R&D % of Revenue
B11: G&A % of Revenue
B12: D&A % of Revenue
B13: Tax Rate %
B14: Capex % of Revenue
B16: Income Statement
B17: Revenue | C17: =FINANCIALS!C8 | D17: =FINANCIALS!D8 | E17: =FINANCIALS!E8 | F17: =FINANCIALS!F8 | G17: =F17*(1+G7) | H17: =G17*(1+H7) | I17: =H17*(1+I7) | J17: =I17*(1+J7) | K17: =J17*(1+K7)
B18: YoY Growth % | G18: =IFERROR(G17/F17-1,"-") | H18: =IFERROR(H17/G17-1,"-") | I18: =IFERROR(I17/H17-1,"-") | J18: =IFERROR(J17/I17-1,"-") | K18: =IFERROR(K17/J17-1,"-")
B19: Gross Profit | C19: =FINANCIALS!C11 | D19: =FINANCIALS!D11 | E19: =FINANCIALS!E11 | F19: =FINANCIALS!F11 | G19: =G17*G8 | H19: =H17*H8 | I19: =I17*I8 | J19: =J17*J8 | K19: =K17*K8
B20: Gross Margin % | C20: =FINANCIALS!C12 | D20: =FINANCIALS!D12 | E20: =FINANCIALS!E12 | F20: =FINANCIALS!F12 | G20: =IFERROR(G19/G17,"-") | H20: =IFERROR(H19/H17,"-") | I20: =IFERROR(I19/I17,"-") | J20: =IFERROR(J19/J17,"-") | K20: =IFERROR(K19/K17,"-")
B21: Sales & Marketing | C21: =FINANCIALS!C13 | D21: =FINANCIALS!D13 | E21: =FINANCIALS!E13 | F21: =FINANCIALS!F13 | G21: =G17*G9 | H21: =H17*H9 | I21: =I17*I9 | J21: =J17*J9 | K21: =K17*K9
B22: Research & Development | C22: =FINANCIALS!C14 | D22: =FINANCIALS!D14 | E22: =FINANCIALS!E14 | F22: =FINANCIALS!F14 | G22: =G17*G10 | H22: =H17*H10 | I22: =I17*I10 | J22: =J17*J10 | K22: =K17*K10
B23: General & Administrative | C23: =FINANCIALS!C15 | D23: =FINANCIALS!D15 | E23: =FINANCIALS!E15 | F23: =FINANCIALS!F15 | G23: =G17*G11 | H23: =H17*H11 | I23: =I17*I11 | J23: =J17*J11 | K23: =K17*K11
B24: Total OpEx | C24: =FINANCIALS!C16 | D24: =FINANCIALS!D16 | E24: =FINANCIALS!E16 | F24: =FINANCIALS!F16 | G24: =G21+G22+G23 | H24: =H21+H22+H23 | I24: =I21+I22+I23 | J24: =J21+J22+J23 | K24: =K21+K22+K23
B25: EBITDA | C25: =FINANCIALS!C17 | D25: =FINANCIALS!D17 | E25: =FINANCIALS!E17 | F25: =FINANCIALS!F17 | G25: =G19-G24 | H25: =H19-H24 | I25: =I19-I24 | J25: =J19-J24 | K25: =K19-K24
B26: EBITDA Margin % | C26: =FINANCIALS!C18 | D26: =FINANCIALS!D18 | E26: =FINANCIALS!E18 | F26: =FINANCIALS!F18 | G26: =IFERROR(G25/G17,"-") | H26: =IFERROR(H25/H17,"-") | I26: =IFERROR(I25/I17,"-") | J26: =IFERROR(J25/J17,"-") | K26: =IFERROR(K25/K17,"-")
B27: D&A | C27: =FINANCIALS!C19 | D27: =FINANCIALS!D19 | E27: =FINANCIALS!E19 | F27: =FINANCIALS!F19 | G27: =G17*G12 | H27: =H17*H12 | I27: =I17*I12 | J27: =J17*J12 | K27: =K17*K12
B28: EBIT | C28: =FINANCIALS!C20 | D28: =FINANCIALS!D20 | E28: =FINANCIALS!E20 | F28: =FINANCIALS!F20 | G28: =G25-G27 | H28: =H25-H27 | I28: =I25-I27 | J28: =J25-J27 | K28: =K25-K27
B29: Interest Expense | C29: =FINANCIALS!C21 | D29: =FINANCIALS!D21 | E29: =FINANCIALS!E21 | F29: =FINANCIALS!F21
B30: EBT | C30: =FINANCIALS!C22 | D30: =FINANCIALS!D22 | E30: =FINANCIALS!E22 | F30: =FINANCIALS!F22 | G30: =G28-G29 | H30: =H28-H29 | I30: =I28-I29 | J30: =J28-J29 | K30: =K28-K29
B31: Tax | C31: =FINANCIALS!C23 | D31: =FINANCIALS!D23 | E31: =FINANCIALS!E23 | F31: =FINANCIALS!F23 | G31: =G30*G13 | H31: =H30*H13 | I31: =I30*I13 | J31: =J30*J13 | K31: =K30*K13
B32: Net Income | C32: =FINANCIALS!C24 | D32: =FINANCIALS!D24 | E32: =FINANCIALS!E24 | F32: =FINANCIALS!F24 | G32: =G30-G31 | H32: =H30-H31 | I32: =I30-I31 | J32: =J30-J31 | K32: =K30-K31
B34: Free Cash Flow
B35: EBITDA | G35: =G25 | H35: =H25 | I35: =I25 | J35: =J25 | K35: =K25
B36: Less: Capex | C36: =FINANCIALS!C34 | D36: =FINANCIALS!D34 | E36: =FINANCIALS!E34 | F36: =FINANCIALS!F34 | G36: =G17*G14 | H36: =H17*H14 | I36: =I17*I14 | J36: =J17*J14 | K36: =K17*K14
B37: Less: Interest
B38: Free Cash Flow | C38: =FINANCIALS!C35 | D38: =FINANCIALS!D35 | E38: =FINANCIALS!E35 | F38: =FINANCIALS!F35 | G38: =G25-G36-G37 | H38: =H25-H36-H37 | I38: =I25-I36-I37 | J38: =J25-J36-J37 | K38: =K25-K36-K37

Sheet DRIVER TREE
B2: Driver Tree — Thesis Decomposition to MOIC
B4: Decompose your investment thesis into MECE value drivers. Map each driver to an NTB and estimate MOIC contribution. MOIC delta = (Upside Exit EV - Base Exit EV) / Entry Equity.
B6: Lvl | C6: Value Driver | D6: Type | E6: NTB Link | F6: Base ($M) | G6: Upside ($M) | H6: MOIC Delta | I6: Evidence | J6: Notes
B7: 1 | C7: Revenue Growth | D7: Revenue | H7: =IFERROR((G7-F7)/INPUTS!B22,"-")
B8: 2 | C8: Organic Growth | D8: Revenue | E8: NTB 1 | H8: =IFERROR((G8-F8)/INPUTS!B22,"-") | I8: Unconfirmed
B9: 2 | C9: Pricing Power | D9: Revenue | E9: NTB 2 | H9: =IFERROR((G9-F9)/INPUTS!B22,"-") | I9: Unconfirmed
B10: 2 | C10: New Markets / GEO | D10: Revenue | E10: NTB 3 | H10: =IFERROR((G10-F10)/INPUTS!B22,"-") | I10: Unconfirmed
B11: 1 | C11: Margin Expansion | D11: Cost | H11: =IFERROR((G11-F11)/INPUTS!B22,"-")
B12: 2 | C12: Gross Margin Lift | D12: Cost | E12: NTB 4 | H12: =IFERROR((G12-F12)/INPUTS!B22,"-") | I12: Unconfirmed
B13: 2 | C13: OpEx Efficiency | D13: Cost | E13: NTB 5 | H13: =IFERROR((G13-F13)/INPUTS!B22,"-") | I13: Unconfirmed
B14: 1 | C14: Multiple Expansion | D14: Multiple | H14: =IFERROR((G14-F14)/INPUTS!B22,"-")
B15: 2 | C15: Sector re-rating | D15: Multiple | H15: =IFERROR((G15-F15)/INPUTS!B22,"-") | I15: Unconfirmed
B16: 2 | C16: M&A premium | D16: Multiple | H16: =IFERROR((G16-F16)/INPUTS!B22,"-") | I16: Unconfirmed
B17: 1 | C17: Financial Engineering | D17: Leverage | H17: =IFERROR((G17-F17)/INPUTS!B22,"-")
B18: 2 | C18: Debt paydown | D18: Leverage | H18: =IFERROR((G18-F18)/INPUTS!B22,"-")
B19: 2 | C19: Refinancing | D19: Leverage | H19: =IFERROR((G19-F19)/INPUTS!B22,"-")
C21: Total MOIC Delta (Sum of Drivers) | H21: =SUM(H7:H20)

Sheet NTB REGISTRY
B2: NTB Registry — Evidence Tracking & MOIC
B4: Track evidence status for each NTB. MOIC sum must be within ±15% of total MOIC (INPUTS tab). Red = gap requiring resolution before Phase 4 draft.
B6: MOIC Tolerance Check: | D6: =IFERROR(SUM(F10:F16)/INPUTS!B22,"-") | E6: =IFERROR(IF(ABS(SUM(F10:F16)/INPUTS!B22 - INPUTS!B22/INPUTS!B22)<=0.15,"PASS — within ±15%","WARN — outside ±15%"),"-")
B7: # | C7: NTB Statement | D7: Evidence Status | E7: Boundability | F7: MOIC Impact ($M) | G7: MOIC (x) | H7: Primary Risk | I7: Information Gaps | J7: Owner | K7: Due Date
B8: NTB 1 | C8: =INPUTS!C54 | D8: Not yet assessed | G8: =IFERROR(F8/INPUTS!B22,"-")
B9: NTB 2 | C9: =INPUTS!C55 | D9: Not yet assessed | G9: =IFERROR(F9/INPUTS!B22,"-")
B10: NTB 3 | C10: =INPUTS!C56 | D10: Not yet assessed | G10: =IFERROR(F10/INPUTS!B22,"-")
B11: NTB 4 | C11: =INPUTS!C57 | D11: Not yet assessed | G11: =IFERROR(F11/INPUTS!B22,"-")
B12: NTB 5 | C12: =INPUTS!C58 | D12: Not yet assessed | G12: =IFERROR(F12/INPUTS!B22,"-")
B13: NTB 6 | C13: =INPUTS!C59 | D13: Not yet assessed | G13: =IFERROR(F13/INPUTS!B22,"-")
B14: NTB 7 | C14: =INPUTS!C60 | D14: Not yet assessed | G14: =IFERROR(F14/INPUTS!B22,"-")
C16: Total | F16: =SUM(F8:F15) | G16: =SUM(G8:G15)

Sheet KPI TREE
B2: KPI Tree — Management Plan Audit
B4: Map management KPIs to financial model line items. Use this to audit budget credibility and track post-close. Green = on track. Orange = watch. Red = behind plan.
B6: Lvl | C6: KPI Name | D6: Category | E6: Financial Model Line | F6: Frequency | G6: Budget | H6: Actual | I6: Variance ($) | J6: Variance % | K6: Status | L6: Notes
B7: NS | C7: NORTH STAR METRIC | D7: Growth | F7: Annual | I7: =IFERROR(H7-G7,"-") | J7: =IFERROR(I7/G7,"-") | K7: N/A
B8: 1 | C8: Revenue | D8: Growth | E8: Financial Model!C8 | F8: Monthly | I8: =IFERROR(H8-G8,"-") | J8: =IFERROR(I8/G8,"-") | K8: N/A
B9: 2 | C9: ARR / Recurring Rev | D9: Growth | F9: Monthly | I9: =IFERROR(H9-G9,"-") | J9: =IFERROR(I9/G9,"-") | K9: N/A
B10: 2 | C10: New Logo ARR | D10: Growth | F10: Monthly | I10: =IFERROR(H10-G10,"-") | J10: =IFERROR(I10/G10,"-") | K10: N/A
B11: 2 | C11: Expansion ARR | D11: Growth | F11: Monthly | I11: =IFERROR(H11-G11,"-") | J11: =IFERROR(I11/G11,"-") | K11: N/A
B12: 2 | C12: Churn ARR | D12: Retention | F12: Monthly | I12: =IFERROR(H12-G12,"-") | J12: =IFERROR(I12/G12,"-") | K12: N/A
B13: 1 | C13: Gross Margin | D13: Margin | E13: Financial Model!C13 | F13: Monthly | I13: =IFERROR(H13-G13,"-") | J13: =IFERROR(I13/G13,"-") | K13: N/A
B14: 2 | C14: COGS per Unit | D14: Margin | F14: Monthly | I14: =IFERROR(H14-G14,"-") | J14: =IFERROR(I14/G14,"-") | K14: N/A
B15: 2 | C15: Hosting/Infrastructure | D15: Margin | F15: Monthly | I15: =IFERROR(H15-G15,"-") | J15: =IFERROR(I15/G15,"-") | K15: N/A
B16: 1 | C16: EBITDA | D16: Margin | E16: Financial Model!C16 | F16: Monthly | I16: =IFERROR(H16-G16,"-") | J16: =IFERROR(I16/G16,"-") | K16: N/A
B17: 2 | C17: S&M Efficiency (CAC) | D17: Efficiency | F17: Monthly | I17: =IFERROR(H17-G17,"-") | J17: =IFERROR(I17/G17,"-") | K17: N/A
B18: 2 | C18: R&D % Revenue | D18: Efficiency | F18: Monthly | I18: =IFERROR(H18-G18,"-") | J18: =IFERROR(I18/G18,"-") | K18: N/A
B19: 2 | C19: G&A % Revenue | D19: Efficiency | F19: Monthly | I19: =IFERROR(H19-G19,"-") | J19: =IFERROR(I19/G19,"-") | K19: N/A
B20: 1 | C20: Customer Metrics | D20: Retention | F20: Quarterly | I20: =IFERROR(H20-G20,"-") | J20: =IFERROR(I20/G20,"-") | K20: N/A
B21: 2 | C21: Net Revenue Retention | D21: Retention | F21: Quarterly | I21: =IFERROR(H21-G21,"-") | J21: =IFERROR(I21/G21,"-") | K21: N/A
B22: 2 | C22: Gross Revenue Retention | D22: Retention | F22: Quarterly | I22: =IFERROR(H22-G22,"-") | J22: =IFERROR(I22/G22,"-") | K22: N/A
B23: 2 | C23: NPS Score | D23: Retention | F23: Quarterly | I23: =IFERROR(H23-G23,"-") | J23: =IFERROR(I23/G23,"-") | K23: N/A
B24: 1 | C24: Go-to-Market | D24: Growth | F24: Monthly | I24: =IFERROR(H24-G24,"-") | J24: =IFERROR(I24/G24,"-") | K24: N/A
B25: 2 | C25: Pipeline Coverage | D25: Growth | F25: Monthly | I25: =IFERROR(H25-G25,"-") | J25: =IFERROR(I25/G25,"-") | K25: N/A
B26: 2 | C26: Win Rate % | D26: Growth | F26: Monthly | I26: =IFERROR(H26-G26,"-") | J26: =IFERROR(I26/G26,"-") | K26: N/A
B27: 2 | C27: ACV per Deal ($K) | D27: Growth | F27: Monthly | I27: =IFERROR(H27-G27,"-") | J27: =IFERROR(I27/G27,"-") | K27: N/A
B28: 2 | C28: Sales Cycle (Days) | D28: Growth | F28: Monthly | I28: =IFERROR(H28-G28,"-") | J28: =IFERROR(I28/G28,"-") | K28: N/A
B29: 1 | C29: Free Cash Flow | D29: Cash | E29: Financial Model!C29 | F29: Monthly | I29: =IFERROR(H29-G29,"-") | J29: =IFERROR(I29/G29,"-") | K29: N/A
B30: 2 | C30: Capex / Revenue | D30: Cash | F30: Monthly | I30: =IFERROR(H30-G30,"-") | J30: =IFERROR(I30/G30,"-") | K30: N/A
B31: 2 | C31: DSO (Days) | D31: Cash | F31: Monthly | I31: =IFERROR(H31-G31,"-") | J31: =IFERROR(I31/G31,"-") | K31: N/A

Sheet MOIC BRIDGE
B2: MOIC Bridge — Entry to Exit
B4: Waterfall from entry equity to exit proceeds. NTB contributions pull from NTB Registry.
B6: Component | C6: Equity Value ($M) | D6: MOIC Contribution | E6: Cumulative MOIC
B7: Entry Equity Invested | C7: =INPUTS!B22 | D7: 1 | E7: =IFERROR(INPUTS!B22/INPUTS!B22,"-")
B8: NTB 1 — [name from INPUTS] | C8: =IFERROR('NTB REGISTRY'!F10,"-") | D8: =IFERROR('NTB REGISTRY'!G10,"-") | E8: =IFERROR(E7+D8,"-")
B9: NTB 2 — [name from INPUTS] | C9: =IFERROR('NTB REGISTRY'!F11,"-") | D9: =IFERROR('NTB REGISTRY'!G11,"-") | E9: =IFERROR(E8+D9,"-")
B10: NTB 3 — [name from INPUTS] | C10: =IFERROR('NTB REGISTRY'!F12,"-") | D10: =IFERROR('NTB REGISTRY'!G12,"-") | E10: =IFERROR(E9+D10,"-")
B11: NTB 4 — [name from INPUTS] | C11: =IFERROR('NTB REGISTRY'!F13,"-") | D11: =IFERROR('NTB REGISTRY'!G13,"-") | E11: =IFERROR(E10+D11,"-")
B12: NTB 5 — [name from INPUTS] | C12: =IFERROR('NTB REGISTRY'!F14,"-") | D12: =IFERROR('NTB REGISTRY'!G14,"-") | E12: =IFERROR(E11+D12,"-")
B13: Multiple Expansion | E13: =IFERROR(E12+D13,"-")
B14: Leverage / Debt Paydown | E14: =IFERROR(E13+D14,"-")
B16: Exit Proceeds (Equity) | C16: =INPUTS!B36 | D16: =IFERROR(INPUTS!B36/INPUTS!B22,"-") | E16: =IFERROR(INPUTS!B36/INPUTS!B22,"-")
